{"__symbolic":"module","version":4,"metadata":{"ThemeMinimaLight":{"__symbolic":"class","decorators":[{"__symbolic":"call","expression":{"__symbolic":"reference","module":"@angular/core","name":"Directive","line":5,"character":1},"arguments":[{"selector":"[ly-theme-minima-light]","providers":[{"__symbolic":"reference","module":"@alyle/ui","name":"LyTheme2","line":8,"character":4},{"provide":{"__symbolic":"reference","module":"@alyle/ui","name":"LY_THEME_NAME","line":9,"character":15},"useValue":"minima-light"}]}]}],"members":{}},"ThemeMinimaDark":{"__symbolic":"class","decorators":[{"__symbolic":"call","expression":{"__symbolic":"reference","module":"@angular/core","name":"Directive","line":14,"character":1},"arguments":[{"selector":"[ly-theme-minima-dark]","providers":[{"__symbolic":"reference","module":"@alyle/ui","name":"LyTheme2","line":17,"character":4},{"provide":{"__symbolic":"reference","module":"@alyle/ui","name":"LY_THEME_NAME","line":18,"character":15},"useValue":"minima-dark"}]}]}],"members":{}},"ThemeMinimaModule":{"__symbolic":"class","decorators":[{"__symbolic":"call","expression":{"__symbolic":"reference","module":"@angular/core","name":"NgModule","line":23,"character":1},"arguments":[{"declarations":[{"__symbolic":"reference","name":"ThemeMinimaDark"},{"__symbolic":"reference","name":"ThemeMinimaLight"}],"exports":[{"__symbolic":"reference","name":"ThemeMinimaDark"},{"__symbolic":"reference","name":"ThemeMinimaLight"}]}]}],"members":{}},"IMinimaTheme":{"__symbolic":"interface"},"MinimaLight":{"__symbolic":"class","extends":{"__symbolic":"reference","name":"ɵa"},"members":{}},"MinimaDark":{"__symbolic":"class","extends":{"__symbolic":"reference","name":"ɵa"},"members":{}},"ɵa":{"__symbolic":"class","extends":{"__symbolic":"reference","module":"@alyle/ui","name":"LyStyleUtils","line":7,"character":32},"members":{}}},"origins":{"ThemeMinimaLight":"./theme","ThemeMinimaDark":"./theme","ThemeMinimaModule":"./theme","IMinimaTheme":"./theme","MinimaLight":"./light","MinimaDark":"./dark","ɵa":"./base"},"importAs":"@alyle/ui/themes/minima"}