{"__symbolic":"module","version":4,"metadata":{"LyField":{"__symbolic":"class","decorators":[{"__symbolic":"call","expression":{"__symbolic":"reference","module":"@angular/core","name":"Component","line":90,"character":1},"arguments":[{"selector":"ly-field","exportAs":"lyFormField","changeDetection":{"__symbolic":"select","expression":{"__symbolic":"reference","module":"@angular/core","name":"ChangeDetectionStrategy","line":94,"character":19},"member":"OnPush"},"encapsulation":{"__symbolic":"select","expression":{"__symbolic":"reference","module":"@angular/core","name":"ViewEncapsulation","line":95,"character":17},"member":"None"},"template":"<div [className]=\"classes.container\" (click)=\"_control && _control.onContainerClick && _control.onContainerClick($event)\">\n  <fieldset [className]=\"classes.fieldset\"><legend #_fieldsetLegend [className]=\"classes.fieldsetSpan\"></legend></fieldset>\n  <div [className]=\"classes.prefix\" *ngIf=\"_prefixChildren.length\" #_prefixContainer>\n    <ng-content select=\"[lyPrefix]\"></ng-content>\n  </div>\n  <div [className]=\"classes.infix\">\n    <ng-content></ng-content>\n    <div [className]=\"classes.label\" *ngIf=\"_isLabel()\" #_labelContainer2>\n      <span #_labelSpan [className]=\"classes.labelSpan\">\n        <ng-container *ngTemplateOutlet=\"_labelTemplate\"></ng-container>\n      </span>\n    </div>\n    <div [className]=\"classes.placeholder\" *ngIf=\"_isPlaceholder() && _control?.empty && (_control?.floatingLabel || floatingLabel)\">\n      <ng-container *ngTemplateOutlet=\"_placeholderTemplate\"></ng-container>\n    </div>\n  </div>\n  <div [className]=\"classes.suffix\" *ngIf=\"_suffixChildren.length\" #_suffixContainer>\n    <ng-content select=\"[lySuffix]\"></ng-content>\n  </div>\n</div>\n\n<div [className]=\"classes.hintContainer\">\n  <div *ngIf=\"_hintChildren.length && (persistentHint || _control?.errorState || _control?.focused)\">\n    <span *ngIf=\"_control.errorState\">\n      <ng-content select=\"ly-error\"></ng-content>\n    </span>\n    <ng-content select=\"ly-hint\"></ng-content>\n  </div>\n</div>\n\n<ng-template #_labelTemplate>\n  <ng-content select=\"ly-label\"></ng-content>\n  <ng-container *ngIf=\"!_labelChild\">\n    <ng-template *ngTemplateOutlet=\"_placeholderTemplate\"></ng-template>\n  </ng-container>\n</ng-template>\n\n<ng-template #_placeholderTemplate>\n  <ng-content select=\"ly-placeholder\"></ng-content>\n  <ng-container *ngIf=\"_control.placeholder\">{{ _control.placeholder }}</ng-container>\n</ng-template>\n"}]}],"members":{"_labelContainer":[{"__symbolic":"property","decorators":[{"__symbolic":"call","expression":{"__symbolic":"reference","module":"@angular/core","name":"ViewChild","line":114,"character":3},"arguments":["_labelContainer",{"static":false}]}]}],"_labelContainer2":[{"__symbolic":"property","decorators":[{"__symbolic":"call","expression":{"__symbolic":"reference","module":"@angular/core","name":"ViewChild","line":115,"character":3},"arguments":["_labelContainer2",{"static":false}]}]}],"_labelSpan":[{"__symbolic":"property","decorators":[{"__symbolic":"call","expression":{"__symbolic":"reference","module":"@angular/core","name":"ViewChild","line":116,"character":3},"arguments":["_labelSpan",{"static":false}]}]}],"_prefixContainer":[{"__symbolic":"property","decorators":[{"__symbolic":"call","expression":{"__symbolic":"reference","module":"@angular/core","name":"ViewChild","line":117,"character":3},"arguments":["_prefixContainer",{"static":false}]}]}],"_suffixContainer":[{"__symbolic":"property","decorators":[{"__symbolic":"call","expression":{"__symbolic":"reference","module":"@angular/core","name":"ViewChild","line":118,"character":3},"arguments":["_suffixContainer",{"static":false}]}]}],"_fieldsetLegend":[{"__symbolic":"property","decorators":[{"__symbolic":"call","expression":{"__symbolic":"reference","module":"@angular/core","name":"ViewChild","line":119,"character":3},"arguments":["_fieldsetLegend",{"static":false}]}]}],"_control":[{"__symbolic":"property","decorators":[{"__symbolic":"call","expression":{"__symbolic":"reference","module":"@angular/core","name":"ContentChild","line":120,"character":3},"arguments":[{"__symbolic":"reference","name":"LyFieldControlBase"},{"static":false}]}]}],"_placeholderChild":[{"__symbolic":"property","decorators":[{"__symbolic":"call","expression":{"__symbolic":"reference","module":"@angular/core","name":"ContentChild","line":121,"character":3},"arguments":[{"__symbolic":"reference","name":"ɵa"},{"static":false}]}]}],"_labelChild":[{"__symbolic":"property","decorators":[{"__symbolic":"call","expression":{"__symbolic":"reference","module":"@angular/core","name":"ContentChild","line":122,"character":3},"arguments":[{"__symbolic":"reference","name":"ɵb"},{"static":false}]}]}],"_hintChildren":[{"__symbolic":"property","decorators":[{"__symbolic":"call","expression":{"__symbolic":"reference","module":"@angular/core","name":"ContentChildren","line":123,"character":3},"arguments":[{"__symbolic":"reference","name":"ɵc"}]}]}],"_prefixChildren":[{"__symbolic":"property","decorators":[{"__symbolic":"call","expression":{"__symbolic":"reference","module":"@angular/core","name":"ContentChildren","line":124,"character":3},"arguments":[{"__symbolic":"reference","name":"ɵd"}]}]}],"_suffixChildren":[{"__symbolic":"property","decorators":[{"__symbolic":"call","expression":{"__symbolic":"reference","module":"@angular/core","name":"ContentChildren","line":125,"character":3},"arguments":[{"__symbolic":"reference","name":"ɵe"}]}]}],"_errorChildren":[{"__symbolic":"property","decorators":[{"__symbolic":"call","expression":{"__symbolic":"reference","module":"@angular/core","name":"ContentChildren","line":126,"character":3},"arguments":[{"__symbolic":"reference","name":"ɵf"}]}]}],"persistentHint":[{"__symbolic":"property","decorators":[{"__symbolic":"call","expression":{"__symbolic":"reference","module":"@angular/core","name":"Input","line":132,"character":3}}]}],"fullWidth":[{"__symbolic":"property","decorators":[{"__symbolic":"call","expression":{"__symbolic":"reference","module":"@angular/core","name":"Input","line":134,"character":3}}]}],"floatingLabel":[{"__symbolic":"property","decorators":[{"__symbolic":"call","expression":{"__symbolic":"reference","module":"@angular/core","name":"Input","line":159,"character":3}}]}],"color":[{"__symbolic":"property","decorators":[{"__symbolic":"call","expression":{"__symbolic":"reference","module":"@angular/core","name":"Input","line":169,"character":3}}]}],"appearance":[{"__symbolic":"property","decorators":[{"__symbolic":"call","expression":{"__symbolic":"reference","module":"@angular/core","name":"Input","line":206,"character":3}}]}],"onFocus":[{"__symbolic":"method","decorators":[{"__symbolic":"call","expression":{"__symbolic":"reference","module":"@angular/core","name":"HostListener","line":223,"character":3},"arguments":["focus"]}]}],"__ctor__":[{"__symbolic":"constructor","parameters":[{"__symbolic":"reference","module":"@angular/core","name":"Renderer2","line":228,"character":23},{"__symbolic":"reference","name":"ElementRef","module":"@angular/core","arguments":[{"__symbolic":"error","message":"Could not resolve type","line":503,"character":28,"context":{"typeName":"HTMLInputElement"},"module":"./field"}]},{"__symbolic":"reference","module":"@alyle/ui","name":"ElementObserver","line":230,"character":30},{"__symbolic":"reference","module":"@alyle/ui","name":"LyTheme2","line":231,"character":20},{"__symbolic":"reference","module":"@angular/core","name":"ChangeDetectorRef","line":232,"character":17},{"__symbolic":"reference","module":"@angular/core","name":"NgZone","line":233,"character":21}]}],"ngOnInit":[{"__symbolic":"method"}],"ngAfterContentInit":[{"__symbolic":"method"}],"ngAfterViewInit":[{"__symbolic":"method"}],"ngOnDestroy":[{"__symbolic":"method"}],"_updateFielset":[{"__symbolic":"method"}],"_updateFielsetSpan":[{"__symbolic":"method"}],"_isLabel":[{"__symbolic":"method"}],"_isPlaceholder":[{"__symbolic":"method"}],"_isEmpty":[{"__symbolic":"method"}],"_updateFloatingLabel":[{"__symbolic":"method"}],"_markForCheck":[{"__symbolic":"method"}],"_getHostElement":[{"__symbolic":"method"}]}},"LyNativeControl":{"__symbolic":"class","decorators":[{"__symbolic":"call","expression":{"__symbolic":"reference","module":"@angular/core","name":"Directive","line":395,"character":1},"arguments":[{"selector":"input[lyInput], textarea[lyInput], input[lyNativeControl], textarea[lyNativeControl], select[lyNativeControl]","exportAs":"LyNativeControl","providers":[{"provide":{"__symbolic":"reference","name":"LyFieldControlBase"},"useExisting":{"__symbolic":"reference","name":"LyNativeControl"}}]}]}],"members":{"_onInput":[{"__symbolic":"method","decorators":[{"__symbolic":"call","expression":{"__symbolic":"reference","module":"@angular/core","name":"HostListener","line":416,"character":3},"arguments":["input"]}]}],"_onBlur":[{"__symbolic":"method","decorators":[{"__symbolic":"call","expression":{"__symbolic":"reference","module":"@angular/core","name":"HostListener","line":420,"character":3},"arguments":["blur"]}]}],"_onFocus":[{"__symbolic":"method","decorators":[{"__symbolic":"call","expression":{"__symbolic":"reference","module":"@angular/core","name":"HostListener","line":426,"character":3},"arguments":["focus"]}]}],"value":[{"__symbolic":"property","decorators":[{"__symbolic":"call","expression":{"__symbolic":"reference","module":"@angular/core","name":"Input","line":434,"character":3}}]}],"disabled":[{"__symbolic":"property","decorators":[{"__symbolic":"call","expression":{"__symbolic":"reference","module":"@angular/core","name":"HostBinding","line":446,"character":3}},{"__symbolic":"call","expression":{"__symbolic":"reference","module":"@angular/core","name":"Input","line":447,"character":3}}]}],"required":[{"__symbolic":"property","decorators":[{"__symbolic":"call","expression":{"__symbolic":"reference","module":"@angular/core","name":"HostBinding","line":475,"character":3}},{"__symbolic":"call","expression":{"__symbolic":"reference","module":"@angular/core","name":"Input","line":476,"character":3}}]}],"placeholder":[{"__symbolic":"property","decorators":[{"__symbolic":"call","expression":{"__symbolic":"reference","module":"@angular/core","name":"Input","line":482,"character":3}}]}],"__ctor__":[{"__symbolic":"constructor","parameterDecorators":[null,null,null,[{"__symbolic":"call","expression":{"__symbolic":"reference","module":"@angular/core","name":"Optional","line":505,"character":5}}],[{"__symbolic":"call","expression":{"__symbolic":"reference","module":"@angular/core","name":"Optional","line":507,"character":5}},{"__symbolic":"call","expression":{"__symbolic":"reference","module":"@angular/core","name":"Self","line":507,"character":17}}],[{"__symbolic":"call","expression":{"__symbolic":"reference","module":"@angular/core","name":"Optional","line":508,"character":5}}],[{"__symbolic":"call","expression":{"__symbolic":"reference","module":"@angular/core","name":"Optional","line":509,"character":5}}]],"parameters":[{"__symbolic":"reference","module":"@alyle/ui","name":"LyTheme2","line":231,"character":20},{"__symbolic":"reference","name":"ElementRef","module":"@angular/core","arguments":[{"__symbolic":"error","message":"Could not resolve type","line":503,"character":28,"context":{"typeName":"HTMLInputElement"},"module":"./field"}]},{"__symbolic":"reference","module":"@angular/core","name":"Renderer2","line":228,"character":23},{"__symbolic":"reference","name":"LyField"},{"__symbolic":"reference","module":"@angular/forms","name":"NgControl","line":507,"character":42},{"__symbolic":"reference","module":"@angular/forms","name":"NgForm","line":508,"character":37},{"__symbolic":"reference","module":"@angular/forms","name":"FormGroupDirective","line":509,"character":42}]}],"ngOnInit":[{"__symbolic":"method"}],"ngDoCheck":[{"__symbolic":"method"}],"ngOnDestroy":[{"__symbolic":"method"}],"onContainerClick":[{"__symbolic":"method"}],"focus":[{"__symbolic":"method"}],"_getHostElement":[{"__symbolic":"method"}],"_hasLabelSelectionOption":[{"__symbolic":"method"}]}},"LyFieldControlBase":{"__symbolic":"class","arity":1,"members":{"onContainerClick":[{"__symbolic":"method"}]}},"LyFieldModule":{"__symbolic":"class","decorators":[{"__symbolic":"call","expression":{"__symbolic":"reference","module":"@angular/core","name":"NgModule","line":11,"character":1},"arguments":[{"imports":[{"__symbolic":"reference","module":"@angular/common","name":"CommonModule","line":13,"character":4},{"__symbolic":"reference","module":"@alyle/ui","name":"LyCommonModule","line":14,"character":4}],"exports":[{"__symbolic":"reference","name":"LyField"},{"__symbolic":"reference","name":"ɵa"},{"__symbolic":"reference","name":"ɵb"},{"__symbolic":"reference","name":"LyNativeControl"},{"__symbolic":"reference","name":"ɵd"},{"__symbolic":"reference","name":"ɵe"},{"__symbolic":"reference","name":"ɵc"},{"__symbolic":"reference","name":"ɵf"},{"__symbolic":"reference","module":"@alyle/ui","name":"LyCommonModule","line":25,"character":4}],"declarations":[{"__symbolic":"reference","name":"LyField"},{"__symbolic":"reference","name":"ɵa"},{"__symbolic":"reference","name":"ɵb"},{"__symbolic":"reference","name":"LyNativeControl"},{"__symbolic":"reference","name":"ɵd"},{"__symbolic":"reference","name":"ɵe"},{"__symbolic":"reference","name":"ɵc"},{"__symbolic":"reference","name":"ɵf"}]}]}],"members":{}},"STYLE_SELECT_ARROW":{"&:after":{"position":"absolute","content":"''","width":0,"height":0,"borderLeft":"0.3125em solid transparent","borderRight":"0.3125em solid transparent","borderTop":"0.3125em solid","top":"50%","after":0,"marginTop":"-0.15625em","pointerEvents":"none"},"$quoted$":["&:after"]},"STYLES":{"__symbolic":"error","message":"Lambda not supported","line":18,"character":22,"module":"./styles"},"ɵa":{"__symbolic":"class","decorators":[{"__symbolic":"call","expression":{"__symbolic":"reference","module":"@angular/core","name":"Directive","line":2,"character":1},"arguments":[{"selector":"ly-field > ly-placeholder"}]}],"members":{}},"ɵb":{"__symbolic":"class","decorators":[{"__symbolic":"call","expression":{"__symbolic":"reference","module":"@angular/core","name":"Directive","line":2,"character":1},"arguments":[{"selector":"ly-field > ly-label"}]}],"members":{}},"ɵc":{"__symbolic":"class","decorators":[{"__symbolic":"call","expression":{"__symbolic":"reference","module":"@angular/core","name":"Directive","line":10,"character":1},"arguments":[{"selector":"ly-field > ly-hint"}]}],"members":{"align":[{"__symbolic":"property","decorators":[{"__symbolic":"call","expression":{"__symbolic":"reference","module":"@angular/core","name":"Input","line":17,"character":3}}]}],"__ctor__":[{"__symbolic":"constructor","parameters":[{"__symbolic":"reference","module":"@angular/core","name":"Renderer2","line":37,"character":23},{"__symbolic":"reference","module":"@angular/core","name":"ElementRef","line":38,"character":17},{"__symbolic":"reference","module":"@alyle/ui","name":"LyTheme2","line":39,"character":20}]}]}},"ɵd":{"__symbolic":"class","decorators":[{"__symbolic":"call","expression":{"__symbolic":"reference","module":"@angular/core","name":"Directive","line":4,"character":1},"arguments":[{"selector":"[lyPrefix]"}]}],"members":{}},"ɵe":{"__symbolic":"class","decorators":[{"__symbolic":"call","expression":{"__symbolic":"reference","module":"@angular/core","name":"Directive","line":4,"character":1},"arguments":[{"selector":"[lySuffix]"}]}],"members":{}},"ɵf":{"__symbolic":"class","decorators":[{"__symbolic":"call","expression":{"__symbolic":"reference","module":"@angular/core","name":"Directive","line":7,"character":1},"arguments":[{"selector":"ly-error"}]}],"members":{"__ctor__":[{"__symbolic":"constructor","parameters":[{"__symbolic":"reference","module":"@angular/core","name":"Renderer2","line":13,"character":14},{"__symbolic":"reference","module":"@angular/core","name":"ElementRef","line":14,"character":8},{"__symbolic":"reference","module":"@alyle/ui","name":"LyTheme2","line":15,"character":20}]}]}}},"origins":{"LyField":"./field","LyNativeControl":"./field","LyFieldControlBase":"./field-control-base","LyFieldModule":"./field.module","STYLE_SELECT_ARROW":"./styles","STYLES":"./styles","ɵa":"./placeholder","ɵb":"./label","ɵc":"./hint","ɵd":"./prefix","ɵe":"./suffix","ɵf":"./error"},"importAs":"@alyle/ui/field"}